pyratfun/__init__.py
pyratfun/core.py
pyratfun-0.1.1.dist-info/LICENSE
pyratfun-0.1.1.dist-info/METADATA
pyratfun-0.1.1.dist-info/WHEEL
pyratfun-0.1.1.dist-info/top_level.txt
pyratfun-0.1.1.dist-info/RECORD
